pyjyutping/__init__.py
pyjyutping/dictionaries.py
pyjyutping/jyutping.py
pyjyutping/data/jyutping_dictionary.json
pyjyutping-1.0.0.dist-info/LICENSE
pyjyutping-1.0.0.dist-info/METADATA
pyjyutping-1.0.0.dist-info/WHEEL
pyjyutping-1.0.0.dist-info/entry_points.txt
pyjyutping-1.0.0.dist-info/top_level.txt
pyjyutping-1.0.0.dist-info/RECORD
