Metadata-Version: 2.1
Name: pyjyutping
Version: 1.0.0
Summary: Chinese text to Jyutping conversion library in Python
Home-page: https://github.com/MacroYau/PyJyutping
Author: Macro Yau
Author-email: macroyau.development@gmail.com
License: MIT
Platform: UNKNOWN
Classifier: Programming Language :: Python
Classifier: License :: OSI Approved :: MIT License
Classifier: Operating System :: OS Independent
